AX3003P/AX3003P.py
AX3003P/__init__.py
AX3003P-0.1.dist-info/LICENSE
AX3003P-0.1.dist-info/METADATA
AX3003P-0.1.dist-info/WHEEL
AX3003P-0.1.dist-info/top_level.txt
AX3003P-0.1.dist-info/RECORD
