Metadata-Version: 2.1
Name: AX3003P
Version: 0.1
Summary: Package for controlling AX-3003P Programmable DC Power Supply
Home-page: https://github.com/Bill2462/AX3003P
Author: Krzysztof Adamkiewicz
Author-email: kadamkiewicz835@gmail.com
License: UNKNOWN
Platform: UNKNOWN
Classifier: Development Status :: 3 - Alpha
Classifier: Intended Audience :: Science/Research
Classifier: Natural Language :: English
Classifier: Operating System :: OS Independent
Classifier: Programming Language :: Python :: 2.7
Classifier: Programming Language :: Python :: 3
Classifier: Programming Language :: Python :: 3.2
Classifier: Programming Language :: Python :: 3.3
Classifier: Programming Language :: Python :: 3.4
Classifier: Programming Language :: Python :: 3.5
Classifier: Programming Language :: Python :: 3.6
Requires-Dist: pyserial
